[
       {
              "name": "HelpFile",
              "isActive": "no",
              "isFolder": "no"
       },
       {
              "name": "CSSMan",
              "isActive": "yes",
              "isFolder": "no"
       },
       {
              "name": "MedPrompt",
              "isActive": "yes",
              "isFolder": "no"
       },
       {
              "name": "Main",
              "isActive": "yes",
              "isFolder": "no",
              "eventHandlerList": [
                     "gmcp.Char.Vitals"
              ]
       },
       {
              "name": "MedChat",
              "isActive": "yes",
              "isFolder": "no"
       }
]